supGecko/__init__.py
supGecko/asm.py
supGecko/consts.py
supGecko/gecko.py
supGecko/utils.py
supGecko-0.1.0a5.dist-info/LICENSE
supGecko-0.1.0a5.dist-info/METADATA
supGecko-0.1.0a5.dist-info/WHEEL
supGecko-0.1.0a5.dist-info/top_level.txt
supGecko-0.1.0a5.dist-info/RECORD
